observable_agent/__init__.py
observable_agent/agent.py
observable_agent/commitment.py
observable_agent/contract.py
observable_agent/execution.py
observable_agent/types.py
observable_agent/verifier.py
observable_agent/observability/datadog.py
observable_agent/verifiers/semantic_verifier.py
observable_agent-0.1.0.dist-info/licenses/LICENSE
observable_agent-0.1.0.dist-info/METADATA
observable_agent-0.1.0.dist-info/WHEEL
observable_agent-0.1.0.dist-info/top_level.txt
observable_agent-0.1.0.dist-info/RECORD
